lhw_send_email/__init__.py
lhw_send_email/send.py
lhw_send_email-0.1.3.dist-info/LICENSE
lhw_send_email-0.1.3.dist-info/METADATA
lhw_send_email-0.1.3.dist-info/WHEEL
lhw_send_email-0.1.3.dist-info/top_level.txt
lhw_send_email-0.1.3.dist-info/RECORD
