Metadata-Version: 2.1
Name: lhw-send-email
Version: 0.1.3
Home-page: https://github.com/Th5200/SendEmail
Author: 骆鸿威
Author-email: 1959415641@qq.com
License: MIT
Classifier: License :: OSI Approved :: MIT License
Requires-Python: >=3.9
License-File: LICENSE
